oso_sdk/__init__.py
oso_sdk/constants.py
oso_sdk/exceptions.py
oso_sdk/py.typed
oso_sdk/integrations/__init__.py
oso_sdk/integrations/fastapi.py
oso_sdk/integrations/flask.py
oso_sdk/integrations/utils.py
oso_sdk-0.3.2.dist-info/METADATA
oso_sdk-0.3.2.dist-info/WHEEL
oso_sdk-0.3.2.dist-info/licenses/LICENSE
oso_sdk-0.3.2.dist-info/RECORD
