Metadata-Version: 2.1
Name: oso-sdk
Version: 0.3.2
Summary: Python integrations for Oso Cloud
Project-URL: Homepage, https://www.osohq.com/
Project-URL: Documentation, https://www.osohq.com/docs
Author-email: Oso Security <support@osohq.com>
License-File: LICENSE
Classifier: Development Status :: 4 - Beta
Classifier: Environment :: Web Environment
Classifier: Intended Audience :: Developers
Classifier: License :: OSI Approved :: Apache Software License
Classifier: Operating System :: OS Independent
Classifier: Programming Language :: Python :: 3 :: Only
Classifier: Programming Language :: Python :: 3.8
Classifier: Programming Language :: Python :: 3.9
Classifier: Programming Language :: Python :: 3.10
Classifier: Programming Language :: Python :: 3.11
Classifier: Topic :: Software Development :: Libraries :: Python Modules
Requires-Python: >=3.8
Requires-Dist: oso-cloud<2,>=1.0.7
Provides-Extra: example
Requires-Dist: uvicorn[standard]>=0.21.0; extra == 'example'
Provides-Extra: fastapi
Requires-Dist: fastapi>=0.79.0; extra == 'fastapi'
Requires-Dist: starlette>=0.19.1; extra == 'fastapi'
Provides-Extra: flask
Requires-Dist: flask>=2.0.0; extra == 'flask'
Provides-Extra: test
Requires-Dist: black==23.1.0; extra == 'test'
Requires-Dist: coverage[toml]>=7.2.1; extra == 'test'
Requires-Dist: fastapi==0.79.0; python_version == '3.8' and extra == 'test'
Requires-Dist: fastapi>=0.79.0; python_version > '3.8' and extra == 'test'
Requires-Dist: flask[async]==2.0.0; python_version == '3.8' and extra == 'test'
Requires-Dist: flask[async]>=2.0.0; python_version > '3.8' and extra == 'test'
Requires-Dist: httpx==0.23.3; extra == 'test'
Requires-Dist: isort==5.12.0; extra == 'test'
Requires-Dist: mypy==1.1.1; extra == 'test'
Requires-Dist: pytest==7.2.2; extra == 'test'
Requires-Dist: ruff==0.0.254; extra == 'test'
Requires-Dist: starlette==0.19.1; python_version == '3.8' and extra == 'test'
Requires-Dist: starlette>=0.19.1; python_version > '3.8' and extra == 'test'
Requires-Dist: werkzeug==2.0.3; python_version == '3.8' and extra == 'test'
Requires-Dist: werkzeug>=2.0.3; python_version >= '3.8' and extra == 'test'
